textual_jumper/__init__.py
textual_jumper/demo.py
textual_jumper/jump_overlay.py
textual_jumper/jumper.py
textual_jumper-0.2.0.dist-info/WHEEL
textual_jumper-0.2.0.dist-info/entry_points.txt
textual_jumper-0.2.0.dist-info/METADATA
textual_jumper-0.2.0.dist-info/RECORD
