Metadata-Version: 2.3
Name: textual-jumper
Version: 0.2.0
Summary: A keyboard-driven navigation widget for Textual TUI applications
Keywords: textual,tui,terminal,navigation,keyboard,vim,easymotion
Author: Zaloog
Author-email: Zaloog <gramslars@gmail.com>
License: MIT
Classifier: Development Status :: 4 - Beta
Classifier: Environment :: Console
Classifier: Intended Audience :: Developers
Classifier: License :: OSI Approved :: MIT License
Classifier: Operating System :: OS Independent
Classifier: Programming Language :: Python :: 3
Classifier: Programming Language :: Python :: 3.10
Classifier: Programming Language :: Python :: 3.11
Classifier: Programming Language :: Python :: 3.12
Classifier: Programming Language :: Python :: 3.13
Classifier: Topic :: Software Development :: Libraries :: Python Modules
Classifier: Topic :: Software Development :: User Interfaces
Classifier: Topic :: Terminals
Classifier: Typing :: Typed
Requires-Dist: textual>=6.3.0
Requires-Dist: pytest>=8.0.0 ; extra == 'dev'
Requires-Dist: pytest-asyncio>=0.23.0 ; extra == 'dev'
Requires-Dist: pytest-cov>=6.0.0 ; extra == 'dev'
Requires-Dist: pre-commit>=4.0.0 ; extra == 'dev'
Requires-Dist: ruff>=0.8.0 ; extra == 'dev'
Requires-Dist: mypy>=1.13.0 ; extra == 'dev'
Requires-Python: >=3.10
Project-URL: Homepage, https://github.com/zaloog/textual-jumper
Project-URL: Issues, https://github.com/zaloog/textual-jumper/issues
Project-URL: Repository, https://github.com/zaloog/textual-jumper
Provides-Extra: dev
